openzl_demo/__init__.py
openzl_demo/_openzl_demo.cpython-310-x86_64-linux-gnu.so
openzl_demo-0.1.1.dist-info/METADATA
openzl_demo-0.1.1.dist-info/WHEEL
openzl_demo-0.1.1.dist-info/RECORD
